mlable/__init__.py
mlable/data.py
mlable/layers.py
mlable/meta.py
mlable/optimizers.py
mlable/sampling.py
mlable/shapes.py
mlable/text.py
mlable/utils.py
mlable_torch-0.2.9.dist-info/METADATA
mlable_torch-0.2.9.dist-info/WHEEL
mlable_torch-0.2.9.dist-info/RECORD
