Metadata-Version: 2.3
Name: mlable-torch
Version: 0.2.9
Summary: PyTorch libs: layers, blocks, optimizers, etc.
License: .github/LICENSE.md
Author: apehex
Author-email: apehex@protonmail.com
Requires-Python: >=3.10,<3.14
Classifier: License :: Other/Proprietary License
Classifier: Programming Language :: Python :: 3
Classifier: Programming Language :: Python :: 3.10
Classifier: Programming Language :: Python :: 3.11
Classifier: Programming Language :: Python :: 3.12
Classifier: Programming Language :: Python :: 3.13
Requires-Dist: numpy (>=2.0)
Requires-Dist: torch (>=2.2)
